mlop/__init__.py
mlop/__main__.py
mlop/api.py
mlop/auth.py
mlop/data.py
mlop/file.py
mlop/iface.py
mlop/init.py
mlop/log.py
mlop/op.py
mlop/sets.py
mlop/store.py
mlop/sys.py
mlop/util.py
mlop/compat/__init__.py
mlop/compat/torch.py
mlop-0.0.2.dist-info/licenses/LICENSE
mlop-0.0.2.dist-info/METADATA
mlop-0.0.2.dist-info/WHEEL
mlop-0.0.2.dist-info/entry_points.txt
mlop-0.0.2.dist-info/top_level.txt
mlop-0.0.2.dist-info/RECORD
