Metadata-Version: 2.4
Name: mlop
Version: 0.0.2
Summary: mlop
Author-email: jqssun <jqssun+git@googlemail.com>, lakeesiv <lakeesivaraya@gmail.com>
License:                     GNU GENERAL PUBLIC LICENSE
Project-URL: Homepage, https://github.com/mlop-ai/mlop
Project-URL: Documentation, https://mlop-ai.github.io/docs/
Project-URL: Repository, https://github.com/mlop-ai/mlop.git
License-File: LICENSE
Requires-Dist: GitPython
Requires-Dist: httpx[http2]
Requires-Dist: keyring
Requires-Dist: pillow
Requires-Dist: psutil
Requires-Dist: rich
Requires-Dist: soundfile
Provides-Extra: full
Requires-Dist: keyrings.alt; extra == "full"
Dynamic: license-file
